{"serial": "33030", "department_serial": 31, "code": "ME3089", "class": "*", "name": {"en": "Engineering Japanese", "ch": "工程日文I"}, "notice": {"en": "", "ch": ""}, "instructor": {"en": ["Yu, Cheu-Chu"], "ch": ["余秋菊"]}, "credits": 3, "time_loc": [{"time": {"week": 4, "session": ["7", "8", "9"]}, "loc": {"building": "E2", "room": "411"}}], "isRequired": false, "isFullSem": false, "MaxStu": 50, "department": {"ch": "機械工程學系", "en": "Department of Mechanical Engineering"}, "system": {"ch": "學士班", "en": "Undergraduate Programme"}, "language": {"ch": "日語", "en": "Japanese"}, "card": {"ch": "部份使用", "en": "Optional"}, "assigned": 5, "selected": 49, "remark": {"ch": "", "en": ""}, "goal": {"ch": "1.以前期所學之基本句型切入動詞變化，了解動詞各項基本活用後， 以實用日語為學習主軸，培養學習者日常的聽．說．讀．寫基礎，透過對話紮實並強化各項能力。 \n2.機械相關文章的導讀", "en": "1.前期習った基礎文型を土台にして、動詞の変化及びその活用を勉強していくうちに、聞く、書く、話す、読むなどの能力深めよう。 \n2.機械学に関する小論文を読める。"}, "outline": {"ch": "1.動詞的分類與變化\n2.動作的進行與要求表現\n3.狀態的持續與維持\n4.動作的允許及禁止表現\n5.動作的接續表現及補述表現\n6.義務表現與非義務句型\n7.動詞句名詞化表現\n8.能力句型\n9.經驗表現及動作的列舉表現\n10.普通形的活用", "en": "1.動詞の変化\n2.動作の進行と要求 表現\n3.状態の持続と維持\n4.動作の許可と禁止\n5.動作接続と補述表現\n6.義務と非義務表現\n7.動詞句名詞化\n8.能力表現\n9.経験と動作の列挙表現?\n10.動詞の普通形"}, "textbook": {"ch": "大家的日本語初級２", "en": "皆の日本語初級2"}, "selfCompiledRate": {"ch": "30", "en": "30"}, "instructMethod": {"ch": "講授\n\n\n個別指導", "en": ["Lecture", "", "", "Individual Instruction"]}, "gradMethod": {"ch": "平時考察（出席,小考,作業,口試）４０％ \n期中考試 ３０％ \n期末考試 ３０％", "en": "期中テスト 30％\n期末テスト 30％\n（出席、テスト、宿題、口頭試験） 40％"}, "officeHour": {"ch": "請自行與老師約時間", "en": "no"}, "teachWeeks": {"ch": "18", "en": "18"}, "flexDiscription": {"ch": "", "en": ""}, "domain": {"ch": "基礎學科", "en": "基礎學科"}, "map": {"ch": [{"competencies": "專業知識與技能", "rating": "(2)低", "assesments": ["紙筆測驗/會考", "作業練習", "出席/課堂表現"]}, {"competencies": "實驗規劃與資料分析", "rating": "(1)非常低", "assesments": ["紙筆測驗/會考"]}, {"competencies": "工程設計與整合", "rating": "(0)無", "assesments": ["紙筆測驗/會考"]}, {"competencies": "合作溝通與管理", "rating": "(3)普通", "assesments": ["紙筆測驗/會考", "口頭報告/口試"]}, {"competencies": "專業倫理與社會責任", "rating": "(1)非常低", "assesments": ["紙筆測驗/會考"]}], "en": [{"competencies": "Engineering Knowledge and Problem Analysis", "rating": "(2)Low", "assesments": ["Test/Exam", "Assignments", "Attendance/Performance"]}, {"competencies": "Experiment and Implementation", "rating": "(1)VeryLow", "assesments": ["Test/Exam"]}, {"competencies": "Design / Development of Solution and Investigation", "rating": "(0)", "assesments": ["Test/Exam"]}, {"competencies": "Communication and Team Work", "rating": "(3)Medium", "assesments": ["Test/Exam", "Presentation/Oral Exam"]}, {"competencies": "The Engineer and Society", "rating": "(1)VeryLow", "assesments": ["Test/Exam"]}]}, "assignCriteria": {"ch": ["系所:限機械工程學系。", "系所:限機械工程學系碩士班、機械工程學系光機電工程碩士班、能源工程研究所碩士班。", "系所:限機械工程學系博士班、機械工程學系光機電工程博士班、能源工程研究所博士班。"], "en": ["Department:Department of Mechanical Engineering only.", "Department:MSc in Mechanical Engineering、Master Program in Opto-Mechatronics Engineering, Department of Mechanical Engineering、MSc in Energy Engineering only.", "Department:PhD in Mechanical Engineering、MSc in Opto-Mechatronics Engineering、PhD in Energy Engineering only."]}, "preselecStu": 34, "stuGender": {"male": 44, "Female": 5}, "stuGrade": {"doctor": {}, "master": {"2": 2, "1": 9}, "bachelor": {"4": 16, "3": 13, "2": 9}}, "stus": [{"serial": "1", "stunum": "10*******", "department": "機械工程學系先進材料與精密製造", "grade": "4", "class": "2", "priority": "1", "isRequired": false, "isPreselected": true, "isManuallySelected": false, "isCodeSelected": false}, {"serial": "2", "stunum": "11*******", "department": "機械工程學系光機電工程組", "grade": "4", "class": "1", "priority": "1", "isRequired": false, "isPreselected": true, "isManuallySelected": false, "isCodeSelected": false}, {"serial": "3", "stunum": "11*******", "department": "機械工程學系光機電工程組", "grade": "4", "class": "1", "priority": "1", "isRequired": false, "isPreselected": true, "isManuallySelected": false, "isCodeSelected": false}, {"serial": "4", "stunum": "11*******", "department": "機械工程學系光機電工程組", "grade": "4", "class": "1", "priority": "1", "isRequired": false, "isPreselected": true, "isManuallySelected": false, "isCodeSelected": false}, {"serial": "5", "stunum": "11*******", "department": "機械工程學系光機電工程組", "grade": "4", "class": "1", "priority": "1", "isRequired": false, "isPreselected": true, "isManuallySelected": false, "isCodeSelected": false}, {"serial": "6", "stunum": "11*******", "department": "機械工程學系先進材料與精密製造", "grade": "4", "class": "2", "priority": "1", "isRequired": false, "isPreselected": true, "isManuallySelected": false, "isCodeSelected": false}, {"serial": "7", "stunum": "11*******", "department": "機械工程學系設計與分析組", "grade": "4", "class": "3", "priority": "1", "isRequired": false, "isPreselected": true, "isManuallySelected": false, "isCodeSelected": false}, {"serial": "8", "stunum": "11*******", "department": "機械工程學系光機電工程組", "grade": "4", "class": "1", "priority": "1", "isRequired": false, "isPreselected": true, "isManuallySelected": false, "isCodeSelected": false}, {"serial": "9", "stunum": "11*******", "department": "機械工程學系先進材料與精密製造", "grade": "4", "class": "2", "priority": "1", "isRequired": false, "isPreselected": false, "isManuallySelected": false, "isCodeSelected": false}, {"serial": "10", "stunum": "11*******", "department": "機械工程學系先進材料與精密製造", "grade": "4", "class": "2", "priority": "1", "isRequired": false, "isPreselected": true, "isManuallySelected": false, "isCodeSelected": false}, {"serial": "11", "stunum": "11*******", "department": "機械工程學系先進材料與精密製造", "grade": "4", "class": "2", "priority": "1", "isRequired": false, "isPreselected": true, "isManuallySelected": false, "isCodeSelected": false}, {"serial": "12", "stunum": "11*******", "department": "機械工程學系設計與分析組", "grade": "4", "class": "3", "priority": "1", "isRequired": false, "isPreselected": true, "isManuallySelected": false, "isCodeSelected": false}, {"serial": "13", "stunum": "11*******", "department": "機械工程學系光機電工程組", "grade": "4", "class": "1", "priority": "1", "isRequired": false, "isPreselected": true, "isManuallySelected": false, "isCodeSelected": false}, {"serial": "14", "stunum": "11*******", "department": "機械工程學系設計與分析組", "grade": "4", "class": "3", "priority": "1", "isRequired": false, "isPreselected": true, "isManuallySelected": false, "isCodeSelected": false}, {"serial": "15", "stunum": "11*******", "department": "機械工程學系設計與分析組", "grade": "4", "class": "3", "priority": "1", "isRequired": false, "isPreselected": true, "isManuallySelected": false, "isCodeSelected": false}, {"serial": "16", "stunum": "11*******", "department": "機械工程學系設計與分析組", "grade": "4", "class": "3", "priority": "1", "isRequired": false, "isPreselected": true, "isManuallySelected": false, "isCodeSelected": false}, {"serial": "17", "stunum": "11*******", "department": "工學院學士班", "grade": "4", "class": "*", "priority": "1", "isRequired": false, "isPreselected": false, "isManuallySelected": false, "isCodeSelected": false}, {"serial": "18", "stunum": "11*******", "department": "機械工程學系光機電工程組", "grade": "3", "class": "1", "priority": "1", "isRequired": false, "isPreselected": true, "isManuallySelected": false, "isCodeSelected": false}, {"serial": "19", "stunum": "11*******", "department": "機械工程學系光機電工程組", "grade": "3", "class": "1", "priority": "1", "isRequired": false, "isPreselected": false, "isManuallySelected": false, "isCodeSelected": false}, {"serial": "20", "stunum": "11*******", "department": "機械工程學系光機電工程組", "grade": "3", "class": "1", "priority": "1", "isRequired": false, "isPreselected": true, "isManuallySelected": false, "isCodeSelected": false}, {"serial": "21", "stunum": "11*******", "department": "機械工程學系設計與分析組", "grade": "3", "class": "3", "priority": "1", "isRequired": false, "isPreselected": true, "isManuallySelected": false, "isCodeSelected": false}, {"serial": "22", "stunum": "11*******", "department": "機械工程學系光機電工程組", "grade": "3", "class": "1", "priority": "1", "isRequired": false, "isPreselected": true, "isManuallySelected": false, "isCodeSelected": false}, {"serial": "23", "stunum": "11*******", "department": "機械工程學系光機電工程組", "grade": "3", "class": "1", "priority": "1", "isRequired": false, "isPreselected": true, "isManuallySelected": false, "isCodeSelected": false}, {"serial": "24", "stunum": "11*******", "department": "機械工程學系光機電工程組", "grade": "3", "class": "1", "priority": "1", "isRequired": false, "isPreselected": true, "isManuallySelected": false, "isCodeSelected": false}, {"serial": "25", "stunum": "11*******", "department": "機械工程學系光機電工程組", "grade": "3", "class": "1", "priority": "1", "isRequired": false, "isPreselected": true, "isManuallySelected": false, "isCodeSelected": false}, {"serial": "26", "stunum": "11*******", "department": "機械工程學系光機電工程組", "grade": "3", "class": "1", "priority": "1", "isRequired": false, "isPreselected": true, "isManuallySelected": false, "isCodeSelected": false}, {"serial": "27", "stunum": "11*******", "department": "機械工程學系光機電工程組", "grade": "3", "class": "1", "priority": "1", "isRequired": false, "isPreselected": true, "isManuallySelected": false, "isCodeSelected": false}, {"serial": "28", "stunum": "11*******", "department": "機械工程學系光機電工程組", "grade": "3", "class": "1", "priority": "1", "isRequired": false, "isPreselected": false, "isManuallySelected": false, "isCodeSelected": false}, {"serial": "29", "stunum": "11*******", "department": "機械工程學系光機電工程組", "grade": "3", "class": "1", "priority": "1", "isRequired": false, "isPreselected": true, "isManuallySelected": false, "isCodeSelected": false}, {"serial": "30", "stunum": "11*******", "department": "機械工程學系先進材料與精密製造", "grade": "3", "class": "2", "priority": "1", "isRequired": false, "isPreselected": true, "isManuallySelected": false, "isCodeSelected": false}, {"serial": "31", "stunum": "11*******", "department": "機械工程學系光機電工程組", "grade": "2", "class": "1", "priority": "1", "isRequired": false, "isPreselected": true, "isManuallySelected": false, "isCodeSelected": false}, {"serial": "32", "stunum": "11*******", "department": "機械工程學系先進材料與精密製造", "grade": "2", "class": "2", "priority": "1", "isRequired": false, "isPreselected": false, "isManuallySelected": false, "isCodeSelected": false}, {"serial": "33", "stunum": "11*******", "department": "機械工程學系先進材料與精密製造", "grade": "2", "class": "2", "priority": "1", "isRequired": false, "isPreselected": true, "isManuallySelected": false, "isCodeSelected": false}, {"serial": "34", "stunum": "11*******", "department": "機械工程學系先進材料與精密製造", "grade": "2", "class": "2", "priority": "1", "isRequired": false, "isPreselected": true, "isManuallySelected": false, "isCodeSelected": false}, {"serial": "35", "stunum": "11*******", "department": "機械工程學系先進材料與精密製造", "grade": "2", "class": "2", "priority": "1", "isRequired": false, "isPreselected": true, "isManuallySelected": false, "isCodeSelected": false}, {"serial": "36", "stunum": "11*******", "department": "機械工程學系先進材料與精密製造", "grade": "2", "class": "2", "priority": "1", "isRequired": false, "isPreselected": false, "isManuallySelected": false, "isCodeSelected": false}, {"serial": "37", "stunum": "11*******", "department": "機械工程學系設計與分析組", "grade": "2", "class": "3", "priority": "1", "isRequired": false, "isPreselected": true, "isManuallySelected": false, "isCodeSelected": false}, {"serial": "38", "stunum": "11*******", "department": "機械工程學系設計與分析組", "grade": "2", "class": "3", "priority": "1", "isRequired": false, "isPreselected": true, "isManuallySelected": false, "isCodeSelected": false}, {"serial": "39", "stunum": "11*******", "department": "機械工程學系設計與分析組", "grade": "2", "class": "3", "priority": "1", "isRequired": false, "isPreselected": true, "isManuallySelected": false, "isCodeSelected": false}, {"serial": "40", "stunum": "11*******", "department": "機械工程學系設計與分析組", "grade": "2", "class": "3", "priority": "1", "isRequired": false, "isPreselected": true, "isManuallySelected": false, "isCodeSelected": false}, {"serial": "41", "stunum": "11*******", "department": "機械工程學系設計與分析組", "grade": "2", "class": "3", "priority": "1", "isRequired": false, "isPreselected": false, "isManuallySelected": false, "isCodeSelected": false}, {"serial": "42", "stunum": "11*******", "department": "機械工程學系碩士班", "grade": "2", "class": "*", "priority": "1", "isRequired": false, "isPreselected": false, "isManuallySelected": false, "isCodeSelected": false}, {"serial": "43", "stunum": "11*******", "department": "機械工程學系光機電工程碩士班", "grade": "2", "class": "*", "priority": "1", "isRequired": false, "isPreselected": false, "isManuallySelected": false, "isCodeSelected": false}, {"serial": "44", "stunum": "11*******", "department": "機械工程學系碩士班", "grade": "1", "class": "*", "priority": "1", "isRequired": false, "isPreselected": false, "isManuallySelected": false, "isCodeSelected": false}, {"serial": "45", "stunum": "11*******", "department": "機械工程學系碩士班", "grade": "1", "class": "*", "priority": "1", "isRequired": false, "isPreselected": false, "isManuallySelected": false, "isCodeSelected": false}, {"serial": "46", "stunum": "11*******", "department": "機械工程學系碩士班", "grade": "1", "class": "*", "priority": "1", "isRequired": false, "isPreselected": false, "isManuallySelected": false, "isCodeSelected": false}, {"serial": "47", "stunum": "11*******", "department": "機械工程學系碩士班", "grade": "1", "class": "*", "priority": "1", "isRequired": false, "isPreselected": false, "isManuallySelected": false, "isCodeSelected": false}, {"serial": "48", "stunum": "11*******", "department": "機械工程學系碩士班", "grade": "1", "class": "*", "priority": "1", "isRequired": false, "isPreselected": false, "isManuallySelected": false, "isCodeSelected": false}, {"serial": "49", "stunum": "11*******", "department": "機械工程學系碩士班", "grade": "1", "class": "*", "priority": "1", "isRequired": false, "isPreselected": false, "isManuallySelected": false, "isCodeSelected": false}, {"serial": "50", "stunum": "11*******", "department": "機械工程學系碩士班", "grade": "1", "class": "*", "priority": "1", "isRequired": false, "isPreselected": false, "isManuallySelected": false, "isCodeSelected": false}, {"serial": "51", "stunum": "11*******", "department": "機械工程學系碩士班", "grade": "1", "class": "*", "priority": "1", "isRequired": false, "isPreselected": false, "isManuallySelected": false, "isCodeSelected": false}, {"serial": "52", "stunum": "11*******", "department": "能源工程研究所碩士班", "grade": "1", "class": "*", "priority": "1", "isRequired": false, "isPreselected": false, "isManuallySelected": false, "isCodeSelected": false}, {"serial": "53", "stunum": "11*******", "department": "能源工程研究所碩士班", "grade": "1", "class": "*", "priority": "1", "isRequired": false, "isPreselected": false, "isManuallySelected": false, "isCodeSelected": false}, {"serial": "54", "stunum": "11*******", "department": "能源工程研究所碩士班", "grade": "1", "class": "*", "priority": "1", "isRequired": false, "isPreselected": false, "isManuallySelected": false, "isCodeSelected": false}]}