{"serial": "21050", "code": "MA7072", "class": "C", "name": {"en": "Seminar Ⅱ", "ch": "書報討論 Ⅱ"}, "instructor": {"en": "Liaw, Sheng-Chyang", "ch": "廖勝強"}, "department": {"en": "Department of Mathematics", "ch": "數學系"}, "system": {"en": "Master/Doctoral Programme", "ch": "碩博同修"}, "time_loc": {"en": [{"time": {"week": 4, "period": ["7"]}, "loc": "Hong-Jing Building 412-1"}, {"time": {"week": 4, "period": ["8"]}, "loc": "Hong-Jing Building 412-1"}], "ch": [{"time": {"week": 4, "period": ["7"]}, "loc": "鴻經館", "room": "412-1"}, {"time": {"week": 4, "period": ["8"]}, "loc": "鴻經館", "room": "412-1"}]}, "required": false, "credits": "2", "isFulSem": false, "lang": {"en": "Chinese", "ch": "國語"}, "crsCard": {"en": "None", "ch": "不使用"}, "max_stu": -1, "assigned": 0, "selected": 0, "remark": {"en": "", "ch": ""}, "goal": {"en": "To learn the latest developments of mathematics.", "ch": "學習最新數學進展"}, "content": {"en": "“This course will mainly cover the following topics:\n1. describes the latest developments in the branch of mathematics .\n2. related literature study.\n3. independent study of special topic.“", "ch": "“本課程主要涵蓋下面主題 :\n1. 介紹數學分支領域最新進展。\n2. 相關文獻研讀指導。\n3. 個別主題的研究。“"}, "textbook": {"en": "Selected papers.", "ch": "Selected papers."}, "self_comp": {"en": "50", "ch": "50"}, "method": {"en": "Lecture Seminar Individual Instruction", "ch": "講授 研討 個別指導"}, "grading": {"en": "Research report", "ch": "交報告"}, "office_hr": {"en": "MON.(am 8:00~12:00)", "ch": "星期一(am 8:00~12:00)"}, "teach_week": {"en": "16+2", "ch": "16+2"}, "flex_desc": {"en": "The  course is 16 weeks, and the 17th and 18th weeks provide online supplementary materials to verify what you have learned in this semester.", "ch": "實體課程16週，第17及18週以線上補充教材提供同學自我學習與驗證本學期所學的相關內容"}, "domain": {"en": "理論數學", "ch": "理論數學"}, "map": {"en": [{"competency": "Professional knowledge", "rate": "(5) Very High", "Assessments": "Assignments ， Presentation/Oral Exam"}, {"competency": "Academic research", "rate": "(5) Very High", "Assessments": "Assignments ， Research Report(printed on paper)"}, {"competency": "Independent thinking", "rate": "(5) Very High", "Assessments": "Presentation/Oral Exam ， Research Report(printed on paper)"}, {"competency": "International vision", "rate": "(5) Very High", "Assessments": "Presentation/Oral Exam ， Research Report(printed on paper)"}, {"competency": "Lifelong Learning", "rate": "(5) Very High", "Assessments": "Presentation/Oral Exam ， Research Report(printed on paper)"}], "ch": [{"competency": "專業知識", "rate": "(5) 非常高", "Assessments": "作業練習 ， 口頭報告/口試"}, {"competency": "學術研究", "rate": "(5) 非常高", "Assessments": "作業練習 ， 專題研究報告(書面)"}, {"competency": "獨立思考", "rate": "(5) 非常高", "Assessments": "口頭報告/口試 ， 專題研究報告(書面)"}, {"competency": "國際視野", "rate": "(5) 非常高", "Assessments": "口頭報告/口試 ， 專題研究報告(書面)"}, {"competency": "終身學習", "rate": "(5) 非常高", "Assessments": "口頭報告/口試 ， 專題研究報告(書面)"}]}, "asign_crite": {"en": [], "ch": []}, "prelim_sel": 0, "gender": {"male": 0, "female": 0}, "stu_depart": {"en": {}, "ch": {}}, "stu_grade": {"Bachelor": {}, "Master": {}, "Doctor": {}}}