{"serial": "18010", "department_serial": 13, "code": "IL4101", "class": "*", "name": {"en": "Philosophical Anthropology and Digital Technology", "ch": "哲學人類學與數位科技"}, "notice": {"en": "", "ch": ""}, "instructor": {"en": ["Huang,Ya-Xian", "Su, Tzu-Ying"], "ch": ["黃雅嫺", "蘇子媖"]}, "credits": 3, "time_loc": [{"time": {"week": 1, "session": ["6", "7", "8"]}, "loc": {"building": "A", "room": "104"}}], "isRequired": false, "isFullSem": false, "MaxStu": 50, "department": {"ch": "文學院學士班", "en": "Interdisciplinary Program of Liberal Arts"}, "system": {"ch": "學士班", "en": "Undergraduate Programme"}, "language": {"ch": "國語", "en": "Chinese"}, "card": {"ch": "部份使用", "en": "Optional"}, "assigned": 36, "selected": 0, "remark": {"ch": "", "en": ""}, "goal": {"ch": "本課程旨在探討哲學人類學與數位科技的交集，研究數位技術如何重塑人類身份、社會互動，以及我們對人類存在意義的理解。學生將透過行動反思理論與實際的關聯，以獲得對數位時代人類條件演變的深入認識。故三周一主題（前兩周哲學人類學理論＋後一周行動反思實作），以四大主題貫串，最終產生可思性作品。", "en": "本課程旨在探討哲學人類學與數位科技的交集，研究數位技術如何重塑人類身份、社會互動，以及我們對人類存在意義的理解。學生將透過行動反思理論與實際的關聯，以獲得對數位時代人類條件演變的深入認識。故三周一主題（前兩周哲學人類學理論＋後一周行動反思實作），以四大主題貫串，最終產生可思性作品。"}, "outline": {"ch": "Week 01(2/17) 導論\nWeek 02(2/24) 人性與身份認同\nWeek 03(3/3) 人性與身份認同\nWeek 04(3/10) 實作：網路與我行動反思(多重帳號的我)\nWeek 05(3/17) 校外參觀\nWeek 06(3/24) 我們的身體：虛擬與現實之間\nWeek 07(3/31) 我們的身體：虛擬與現實之間\nWeek 08(4/7) 實作：VTuber (跨性別換置)\nWeek 09(4/14) 數據倫理與隱私\nWeek 10(4/21) 數據倫理與隱私\nWeek 11(4/28) 實作：無限揭露(24小時被觀察)\nWeek 12(5/5) 迎向賽博格公民的未來\nWeek 13(5/12) 迎向賽博格公民的未來\nWeek 14(5/19) 實作：忒修斯之船\nWeek 15(5/26) 課程總結\nWeek 16(6/2) 期末呈現 (實體展)", "en": "Week 01(2/17) 導論\nWeek 02(2/24) 人性與身份認同\nWeek 03(3/3) 人性與身份認同\nWeek 04(3/10) 實作：網路與我行動反思(多重帳號的我)\nWeek 05(3/17) 校外參觀\nWeek 06(3/24) 我們的身體：虛擬與現實之間\nWeek 07(3/31) 我們的身體：虛擬與現實之間\nWeek 08(4/7) 實作：VTuber (跨性別換置)\nWeek 09(4/14) 數據倫理與隱私\nWeek 10(4/21) 數據倫理與隱私\nWeek 11(4/28) 實作：無限揭露(24小時被觀察)\nWeek 12(5/5) 迎向賽博格公民的未來\nWeek 13(5/12) 迎向賽博格公民的未來\nWeek 14(5/19) 實作：忒修斯之船\nWeek 15(5/26) 課程總結\nWeek 16(6/2) 期末呈現 (實體展)"}, "textbook": {"ch": "1. 楊儒賓，《儒家身體觀》，臺北：中央研究院中國文哲研究所，1999。 \n2. 吳光明，〈莊子的身體思維〉蔡麗玲譯，《中國古代思想中的氣論及身體觀》，臺北：巨流圖書公司，1994，頁393-414。 \n3. 鍾雲鶯，〈身與體：《易經》儒家身體觀所呈現的兩個面向〉，《佛學與科學》， 11.1(2010): 21-28。 \n4. 馬克．科克爾伯格 著，鄭楷立 譯，《AI世代：從政治哲學反思人工智慧的衝擊》，台北：商周出版，2024。 \n5. 亞蘭．米龍 著，林德祐 著，《虛擬真實：我們的身體在或不在》，台北：漫遊者出版社，2021。 \n6. 王威智，〈展演VTuber：編織現實與虛構的同伴物種〉，《中外文學》 53卷3期 (2024 / 09) Pp. 213-252。", "en": "1. 楊儒賓，《儒家身體觀》，臺北：中央研究院中國文哲研究所，1999。 \n2. 吳光明，〈莊子的身體思維〉蔡麗玲譯，《中國古代思想中的氣論及身體觀》，臺北：巨流圖書公司，1994，頁393-414。 \n3. 鍾雲鶯，〈身與體：《易經》儒家身體觀所呈現的兩個面向〉，《佛學與科學》， 11.1(2010): 21-28。 \n4. 馬克．科克爾伯格 著，鄭楷立 譯，《AI世代：從政治哲學反思人工智慧的衝擊》，台北：商周出版，2024。 \n5. 亞蘭．米龍 著，林德祐 著，《虛擬真實：我們的身體在或不在》，台北：漫遊者出版社，2021。 \n6. 王威智，〈展演VTuber：編織現實與虛構的同伴物種〉，《中外文學》 53卷3期 (2024 / 09) Pp. 213-252。"}, "selfCompiledRate": {"ch": "20", "en": "20"}, "instructMethod": {"ch": "講授\n研討\n實習/實驗\n個別指導", "en": ["Lecture", "Seminar", "Practical Training Lab", "Individual Instruction"]}, "gradMethod": {"ch": "出席與討論：20％ \n期中成績：四次行動反思 40％ (每次行動反思各10％) \n期末策展：40％", "en": "出席與討論：20％ \n期中成績：四次行動反思 40％ (每次行動反思各10％) \n期末策展：40％"}, "officeHour": {"ch": "週四 13:00-15:00", "en": "週四 13:00-15:00"}, "teachWeeks": {"ch": "16+2", "en": "16+2"}, "flexDiscription": {"ch": "第17、18週自主學習，個別指導，可將期末專題延伸投遞研討會", "en": "第17、18週自主學習，個別指導，可將期末專題延伸投遞研討會"}, "domain": {"ch": "哲學", "en": "哲學"}, "map": {"ch": [{"competencies": "人文實踐", "rating": "(5)非常高", "assesments": ["口頭報告/口試", "實作/實驗", "作品/創作展演"]}, {"competencies": "批判思考", "rating": "(5)非常高", "assesments": ["口頭報告/口試", "實作/實驗", "出席/課堂表現"]}, {"competencies": "多元敘事", "rating": "(5)非常高", "assesments": ["口頭報告/口試", "出席/課堂表現"]}, {"competencies": "跨域學習", "rating": "(5)非常高", "assesments": ["口頭報告/口試", "實作/實驗", "作品/創作展演"]}, {"competencies": "組織合作", "rating": "(5)非常高", "assesments": ["口頭報告/口試", "實作/實驗", "出席/課堂表現", "作品/創作展演"]}], "en": [{"competencies": "人文實踐", "rating": "(5)VeryHigh", "assesments": ["Presentation/Oral Exam", "Practices/Experiments", "Products/Creative Performance"]}, {"competencies": "批判思考", "rating": "(5)VeryHigh", "assesments": ["Presentation/Oral Exam", "Practices/Experiments", "Attendance/Performance"]}, {"competencies": "多元敘事", "rating": "(5)VeryHigh", "assesments": ["Presentation/Oral Exam", "Attendance/Performance"]}, {"competencies": "跨域學習", "rating": "(5)VeryHigh", "assesments": ["Presentation/Oral Exam", "Practices/Experiments", "Products/Creative Performance"]}, {"competencies": "組織合作", "rating": "(5)VeryHigh", "assesments": ["Presentation/Oral Exam", "Practices/Experiments", "Attendance/Performance", "Products/Creative Performance"]}]}, "assignCriteria": {"ch": ["系所:限文學院學士班。"], "en": ["Department:Interdisciplinary Program of Liberal Arts only."]}, "preselecStu": 0, "stuGender": {"male": 0, "Female": 0}, "stuGrade": {"doctor": {}, "master": {}, "bachelor": {}}, "stus": [{"serial": "1", "stunum": "11*******", "department": "文學院學士班", "grade": "4", "class": "*", "priority": "1", "isRequired": false, "isPreselected": false, "isManuallySelected": false, "isCodeSelected": false}, {"serial": "2", "stunum": "11*******", "department": "文學院學士班", "grade": "4", "class": "*", "priority": "1", "isRequired": false, "isPreselected": false, "isManuallySelected": false, "isCodeSelected": false}, {"serial": "3", "stunum": "11*******", "department": "文學院學士班", "grade": "4", "class": "*", "priority": "1", "isRequired": false, "isPreselected": false, "isManuallySelected": false, "isCodeSelected": false}, {"serial": "4", "stunum": "11*******", "department": "文學院學士班", "grade": "4", "class": "*", "priority": "1", "isRequired": false, "isPreselected": false, "isManuallySelected": false, "isCodeSelected": false}, {"serial": "5", "stunum": "11*******", "department": "文學院學士班", "grade": "4", "class": "*", "priority": "1", "isRequired": false, "isPreselected": false, "isManuallySelected": false, "isCodeSelected": false}, {"serial": "6", "stunum": "11*******", "department": "文學院學士班", "grade": "4", "class": "*", "priority": "1", "isRequired": false, "isPreselected": false, "isManuallySelected": false, "isCodeSelected": false}, {"serial": "7", "stunum": "11*******", "department": "文學院學士班", "grade": "4", "class": "*", "priority": "1", "isRequired": false, "isPreselected": false, "isManuallySelected": false, "isCodeSelected": false}, {"serial": "8", "stunum": "11*******", "department": "文學院學士班", "grade": "4", "class": "*", "priority": "1", "isRequired": false, "isPreselected": false, "isManuallySelected": false, "isCodeSelected": false}, {"serial": "9", "stunum": "11*******", "department": "文學院學士班", "grade": "4", "class": "*", "priority": "1", "isRequired": false, "isPreselected": false, "isManuallySelected": false, "isCodeSelected": false}, {"serial": "10", "stunum": "11*******", "department": "文學院學士班", "grade": "4", "class": "*", "priority": "1", "isRequired": false, "isPreselected": false, "isManuallySelected": false, "isCodeSelected": false}, {"serial": "11", "stunum": "11*******", "department": "光電科學與工程學系", "grade": "4", "class": "*", "priority": "1", "isRequired": false, "isPreselected": false, "isManuallySelected": false, "isCodeSelected": false}, {"serial": "12", "stunum": "11*******", "department": "光電科學與工程學系", "grade": "4", "class": "*", "priority": "1", "isRequired": false, "isPreselected": false, "isManuallySelected": false, "isCodeSelected": false}, {"serial": "13", "stunum": "11*******", "department": "光電科學與工程學系", "grade": "4", "class": "*", "priority": "1", "isRequired": false, "isPreselected": false, "isManuallySelected": false, "isCodeSelected": false}, {"serial": "14", "stunum": "11*******", "department": "中國文學系", "grade": "3", "class": "*", "priority": "1", "isRequired": false, "isPreselected": false, "isManuallySelected": false, "isCodeSelected": false}, {"serial": "15", "stunum": "11*******", "department": "文學院學士班", "grade": "2", "class": "*", "priority": "1", "isRequired": false, "isPreselected": false, "isManuallySelected": false, "isCodeSelected": false}, {"serial": "16", "stunum": "11*******", "department": "文學院學士班", "grade": "3", "class": "*", "priority": "1", "isRequired": false, "isPreselected": false, "isManuallySelected": false, "isCodeSelected": false}, {"serial": "17", "stunum": "11*******", "department": "文學院學士班", "grade": "3", "class": "*", "priority": "1", "isRequired": false, "isPreselected": false, "isManuallySelected": false, "isCodeSelected": false}, {"serial": "18", "stunum": "11*******", "department": "文學院學士班", "grade": "3", "class": "*", "priority": "1", "isRequired": false, "isPreselected": false, "isManuallySelected": false, "isCodeSelected": false}, {"serial": "19", "stunum": "11*******", "department": "文學院學士班", "grade": "3", "class": "*", "priority": "1", "isRequired": false, "isPreselected": false, "isManuallySelected": false, "isCodeSelected": false}, {"serial": "20", "stunum": "11*******", "department": "資訊電機學院學士班", "grade": "3", "class": "*", "priority": "1", "isRequired": false, "isPreselected": false, "isManuallySelected": false, "isCodeSelected": false}, {"serial": "21", "stunum": "11*******", "department": "文學院學士班", "grade": "2", "class": "*", "priority": "1", "isRequired": false, "isPreselected": false, "isManuallySelected": false, "isCodeSelected": false}, {"serial": "22", "stunum": "11*******", "department": "文學院學士班", "grade": "2", "class": "*", "priority": "1", "isRequired": false, "isPreselected": false, "isManuallySelected": false, "isCodeSelected": false}, {"serial": "23", "stunum": "11*******", "department": "文學院學士班", "grade": "2", "class": "*", "priority": "1", "isRequired": false, "isPreselected": false, "isManuallySelected": false, "isCodeSelected": false}, {"serial": "24", "stunum": "11*******", "department": "文學院學士班", "grade": "2", "class": "*", "priority": "1", "isRequired": false, "isPreselected": false, "isManuallySelected": false, "isCodeSelected": false}, {"serial": "25", "stunum": "11*******", "department": "文學院學士班", "grade": "2", "class": "*", "priority": "1", "isRequired": false, "isPreselected": false, "isManuallySelected": false, "isCodeSelected": false}, {"serial": "26", "stunum": "11*******", "department": "文學院學士班", "grade": "2", "class": "*", "priority": "1", "isRequired": false, "isPreselected": false, "isManuallySelected": false, "isCodeSelected": false}, {"serial": "27", "stunum": "11*******", "department": "文學院學士班", "grade": "2", "class": "*", "priority": "1", "isRequired": false, "isPreselected": false, "isManuallySelected": false, "isCodeSelected": false}, {"serial": "28", "stunum": "11*******", "department": "文學院學士班", "grade": "2", "class": "*", "priority": "1", "isRequired": false, "isPreselected": false, "isManuallySelected": false, "isCodeSelected": false}, {"serial": "29", "stunum": "11*******", "department": "文學院學士班", "grade": "2", "class": "*", "priority": "1", "isRequired": false, "isPreselected": false, "isManuallySelected": false, "isCodeSelected": false}, {"serial": "30", "stunum": "11*******", "department": "土木工程學系", "grade": "2", "class": "2", "priority": "1", "isRequired": false, "isPreselected": false, "isManuallySelected": false, "isCodeSelected": false}, {"serial": "31", "stunum": "11*******", "department": "文學院學士班", "grade": "2", "class": "*", "priority": "1", "isRequired": false, "isPreselected": false, "isManuallySelected": false, "isCodeSelected": false}, {"serial": "32", "stunum": "11*******", "department": "文學院學士班", "grade": "2", "class": "*", "priority": "1", "isRequired": false, "isPreselected": false, "isManuallySelected": false, "isCodeSelected": false}, {"serial": "33", "stunum": "11*******", "department": "英美語文學系", "grade": "1", "class": "*", "priority": "1", "isRequired": false, "isPreselected": false, "isManuallySelected": false, "isCodeSelected": false}, {"serial": "34", "stunum": "11*******", "department": "文學院學士班", "grade": "1", "class": "*", "priority": "1", "isRequired": false, "isPreselected": false, "isManuallySelected": false, "isCodeSelected": false}, {"serial": "35", "stunum": "11*******", "department": "文學院學士班", "grade": "1", "class": "*", "priority": "1", "isRequired": false, "isPreselected": false, "isManuallySelected": false, "isCodeSelected": false}, {"serial": "36", "stunum": "11*******", "department": "文學院學士班", "grade": "1", "class": "*", "priority": "1", "isRequired": false, "isPreselected": false, "isManuallySelected": false, "isCodeSelected": false}]}