{"serial": "51028", "department_serial": 50, "code": "EE3053", "class": "*", "name": {"en": "Special Project of Circuit Design Techniques", "ch": "電子專題"}, "notice": {"en": "", "ch": "電機系三四年級可修。選修此門課限專題指導老師為電子組教師，同學請務必填寫「專題指導教師同意書」並於加退選期間交回系辦領取密碼卡"}, "instructor": {"en": [], "ch": []}, "credits": 3, "time_loc": [{"time": {"week": 6, "session": ["A", "B", "C"]}, "loc": {"building": "E1", "room": "121"}}], "isRequired": false, "isFullSem": false, "MaxStu": -1, "department": {"ch": "電機工程學系", "en": "Department of Electrical Engineering"}, "system": {"ch": "學士班", "en": "Undergraduate Programme"}, "language": {"ch": "國語", "en": "Chinese"}, "card": {"ch": "全部使用", "en": "All"}, "assigned": 0, "selected": 66, "remark": {"ch": "電機系三四年級可修。選修此門課限專題指導老師為電子組教師，同學請務必填寫「專題指導教師同意書」並於加退選期間交回系辦領取密碼卡", "en": ""}, "goal": {"ch": "", "en": ""}, "outline": {"ch": "", "en": ""}, "textbook": {"ch": "", "en": ""}, "selfCompiledRate": {"ch": "0", "en": "0"}, "instructMethod": {"ch": "", "en": [""]}, "gradMethod": {"ch": "", "en": ""}, "officeHour": {"ch": "", "en": ""}, "teachWeeks": {"ch": "18", "en": "18"}, "flexDiscription": {"ch": "", "en": ""}, "domain": {"ch": "", "en": ""}, "map": {"ch": [], "en": []}, "assignCriteria": {"ch": [], "en": []}, "preselecStu": 0, "stuGender": {"male": 52, "Female": 14}, "stuGrade": {"doctor": {}, "master": {}, "bachelor": {"3": 62, "4": 4}}, "stus": [{"serial": "1", "stunum": "11*******", "department": "電機工程學系", "grade": "3", "class": "1", "priority": "1", "isRequired": false, "isPreselected": false, "isManuallySelected": false, "isCodeSelected": true}, {"serial": "2", "stunum": "11*******", "department": "電機工程學系", "grade": "4", "class": "2", "priority": "1", "isRequired": false, "isPreselected": false, "isManuallySelected": false, "isCodeSelected": true}, {"serial": "3", "stunum": "11*******", "department": "電機工程學系", "grade": "4", "class": "2", "priority": "1", "isRequired": false, "isPreselected": false, "isManuallySelected": false, "isCodeSelected": true}, {"serial": "4", "stunum": "11*******", "department": "電機工程學系", "grade": "4", "class": "2", "priority": "1", "isRequired": false, "isPreselected": false, "isManuallySelected": false, "isCodeSelected": true}, {"serial": "5", "stunum": "11*******", "department": "電機工程學系", "grade": "4", "class": "2", "priority": "1", "isRequired": false, "isPreselected": false, "isManuallySelected": false, "isCodeSelected": true}, {"serial": "6", "stunum": "11*******", "department": "電機工程學系", "grade": "3", "class": "1", "priority": "1", "isRequired": false, "isPreselected": false, "isManuallySelected": false, "isCodeSelected": true}, {"serial": "7", "stunum": "11*******", "department": "電機工程學系", "grade": "3", "class": "1", "priority": "1", "isRequired": false, "isPreselected": false, "isManuallySelected": false, "isCodeSelected": true}, {"serial": "8", "stunum": "11*******", "department": "電機工程學系", "grade": "3", "class": "1", "priority": "1", "isRequired": false, "isPreselected": false, "isManuallySelected": false, "isCodeSelected": true}, {"serial": "9", "stunum": "11*******", "department": "電機工程學系", "grade": "3", "class": "2", "priority": "1", "isRequired": false, "isPreselected": false, "isManuallySelected": false, "isCodeSelected": true}, {"serial": "10", "stunum": "11*******", "department": "電機工程學系", "grade": "3", "class": "2", "priority": "1", "isRequired": false, "isPreselected": false, "isManuallySelected": false, "isCodeSelected": true}, {"serial": "11", "stunum": "11*******", "department": "電機工程學系", "grade": "3", "class": "2", "priority": "1", "isRequired": false, "isPreselected": false, "isManuallySelected": false, "isCodeSelected": true}, {"serial": "12", "stunum": "11*******", "department": "電機工程學系", "grade": "3", "class": "1", "priority": "1", "isRequired": false, "isPreselected": false, "isManuallySelected": false, "isCodeSelected": true}, {"serial": "13", "stunum": "11*******", "department": "電機工程學系", "grade": "3", "class": "1", "priority": "1", "isRequired": false, "isPreselected": false, "isManuallySelected": false, "isCodeSelected": true}, {"serial": "14", "stunum": "11*******", "department": "電機工程學系", "grade": "3", "class": "1", "priority": "1", "isRequired": false, "isPreselected": false, "isManuallySelected": false, "isCodeSelected": true}, {"serial": "15", "stunum": "11*******", "department": "電機工程學系", "grade": "3", "class": "1", "priority": "1", "isRequired": false, "isPreselected": false, "isManuallySelected": false, "isCodeSelected": true}, {"serial": "16", "stunum": "11*******", "department": "電機工程學系", "grade": "3", "class": "1", "priority": "1", "isRequired": false, "isPreselected": false, "isManuallySelected": false, "isCodeSelected": true}, {"serial": "17", "stunum": "11*******", "department": "電機工程學系", "grade": "3", "class": "1", "priority": "1", "isRequired": false, "isPreselected": false, "isManuallySelected": false, "isCodeSelected": true}, {"serial": "18", "stunum": "11*******", "department": "電機工程學系", "grade": "3", "class": "2", "priority": "1", "isRequired": false, "isPreselected": false, "isManuallySelected": false, "isCodeSelected": true}, {"serial": "19", "stunum": "11*******", "department": "電機工程學系", "grade": "3", "class": "2", "priority": "1", "isRequired": false, "isPreselected": false, "isManuallySelected": false, "isCodeSelected": true}, {"serial": "20", "stunum": "11*******", "department": "電機工程學系", "grade": "3", "class": "2", "priority": "1", "isRequired": false, "isPreselected": false, "isManuallySelected": false, "isCodeSelected": true}, {"serial": "21", "stunum": "11*******", "department": "電機工程學系", "grade": "3", "class": "2", "priority": "1", "isRequired": false, "isPreselected": false, "isManuallySelected": false, "isCodeSelected": true}, {"serial": "22", "stunum": "11*******", "department": "電機工程學系", "grade": "3", "class": "2", "priority": "1", "isRequired": false, "isPreselected": false, "isManuallySelected": false, "isCodeSelected": true}, {"serial": "23", "stunum": "11*******", "department": "電機工程學系", "grade": "3", "class": "2", "priority": "1", "isRequired": false, "isPreselected": false, "isManuallySelected": false, "isCodeSelected": true}, {"serial": "24", "stunum": "11*******", "department": "電機工程學系", "grade": "3", "class": "2", "priority": "1", "isRequired": false, "isPreselected": false, "isManuallySelected": false, "isCodeSelected": true}, {"serial": "25", "stunum": "11*******", "department": "電機工程學系", "grade": "3", "class": "1", "priority": "1", "isRequired": false, "isPreselected": false, "isManuallySelected": false, "isCodeSelected": true}, {"serial": "26", "stunum": "11*******", "department": "電機工程學系", "grade": "3", "class": "1", "priority": "1", "isRequired": false, "isPreselected": false, "isManuallySelected": false, "isCodeSelected": true}, {"serial": "27", "stunum": "11*******", "department": "電機工程學系", "grade": "3", "class": "1", "priority": "1", "isRequired": false, "isPreselected": false, "isManuallySelected": false, "isCodeSelected": true}, {"serial": "28", "stunum": "11*******", "department": "電機工程學系", "grade": "3", "class": "1", "priority": "1", "isRequired": false, "isPreselected": false, "isManuallySelected": false, "isCodeSelected": true}, {"serial": "29", "stunum": "11*******", "department": "電機工程學系", "grade": "3", "class": "1", "priority": "1", "isRequired": false, "isPreselected": false, "isManuallySelected": false, "isCodeSelected": true}, {"serial": "30", "stunum": "11*******", "department": "電機工程學系", "grade": "3", "class": "1", "priority": "1", "isRequired": false, "isPreselected": false, "isManuallySelected": false, "isCodeSelected": true}, {"serial": "31", "stunum": "11*******", "department": "電機工程學系", "grade": "3", "class": "1", "priority": "1", "isRequired": false, "isPreselected": false, "isManuallySelected": false, "isCodeSelected": true}, {"serial": "32", "stunum": "11*******", "department": "電機工程學系", "grade": "3", "class": "1", "priority": "1", "isRequired": false, "isPreselected": false, "isManuallySelected": false, "isCodeSelected": true}, {"serial": "33", "stunum": "11*******", "department": "電機工程學系", "grade": "3", "class": "1", "priority": "1", "isRequired": false, "isPreselected": false, "isManuallySelected": false, "isCodeSelected": true}, {"serial": "34", "stunum": "11*******", "department": "電機工程學系", "grade": "3", "class": "1", "priority": "1", "isRequired": false, "isPreselected": false, "isManuallySelected": false, "isCodeSelected": true}, {"serial": "35", "stunum": "11*******", "department": "電機工程學系", "grade": "3", "class": "1", "priority": "1", "isRequired": false, "isPreselected": false, "isManuallySelected": false, "isCodeSelected": true}, {"serial": "36", "stunum": "11*******", "department": "電機工程學系", "grade": "3", "class": "1", "priority": "1", "isRequired": false, "isPreselected": false, "isManuallySelected": false, "isCodeSelected": true}, {"serial": "37", "stunum": "11*******", "department": "電機工程學系", "grade": "3", "class": "1", "priority": "1", "isRequired": false, "isPreselected": false, "isManuallySelected": false, "isCodeSelected": true}, {"serial": "38", "stunum": "11*******", "department": "電機工程學系", "grade": "3", "class": "1", "priority": "1", "isRequired": false, "isPreselected": false, "isManuallySelected": false, "isCodeSelected": true}, {"serial": "39", "stunum": "11*******", "department": "電機工程學系", "grade": "3", "class": "1", "priority": "1", "isRequired": false, "isPreselected": false, "isManuallySelected": false, "isCodeSelected": true}, {"serial": "40", "stunum": "11*******", "department": "電機工程學系", "grade": "3", "class": "1", "priority": "1", "isRequired": false, "isPreselected": false, "isManuallySelected": false, "isCodeSelected": true}, {"serial": "41", "stunum": "11*******", "department": "電機工程學系", "grade": "3", "class": "1", "priority": "1", "isRequired": false, "isPreselected": false, "isManuallySelected": false, "isCodeSelected": true}, {"serial": "42", "stunum": "11*******", "department": "電機工程學系", "grade": "3", "class": "1", "priority": "1", "isRequired": false, "isPreselected": false, "isManuallySelected": false, "isCodeSelected": true}, {"serial": "43", "stunum": "11*******", "department": "電機工程學系", "grade": "3", "class": "1", "priority": "1", "isRequired": false, "isPreselected": false, "isManuallySelected": false, "isCodeSelected": true}, {"serial": "44", "stunum": "11*******", "department": "電機工程學系", "grade": "3", "class": "1", "priority": "1", "isRequired": false, "isPreselected": false, "isManuallySelected": false, "isCodeSelected": true}, {"serial": "45", "stunum": "11*******", "department": "電機工程學系", "grade": "3", "class": "1", "priority": "1", "isRequired": false, "isPreselected": false, "isManuallySelected": false, "isCodeSelected": true}, {"serial": "46", "stunum": "11*******", "department": "電機工程學系", "grade": "3", "class": "1", "priority": "1", "isRequired": false, "isPreselected": false, "isManuallySelected": false, "isCodeSelected": true}, {"serial": "47", "stunum": "11*******", "department": "電機工程學系", "grade": "3", "class": "1", "priority": "1", "isRequired": false, "isPreselected": false, "isManuallySelected": false, "isCodeSelected": true}, {"serial": "48", "stunum": "11*******", "department": "電機工程學系", "grade": "3", "class": "2", "priority": "1", "isRequired": false, "isPreselected": false, "isManuallySelected": false, "isCodeSelected": true}, {"serial": "49", "stunum": "11*******", "department": "電機工程學系", "grade": "3", "class": "2", "priority": "1", "isRequired": false, "isPreselected": false, "isManuallySelected": false, "isCodeSelected": true}, {"serial": "50", "stunum": "11*******", "department": "電機工程學系", "grade": "3", "class": "2", "priority": "1", "isRequired": false, "isPreselected": false, "isManuallySelected": false, "isCodeSelected": true}, {"serial": "51", "stunum": "11*******", "department": "電機工程學系", "grade": "3", "class": "2", "priority": "1", "isRequired": false, "isPreselected": false, "isManuallySelected": false, "isCodeSelected": true}, {"serial": "52", "stunum": "11*******", "department": "電機工程學系", "grade": "3", "class": "2", "priority": "1", "isRequired": false, "isPreselected": false, "isManuallySelected": false, "isCodeSelected": true}, {"serial": "53", "stunum": "11*******", "department": "電機工程學系", "grade": "3", "class": "2", "priority": "1", "isRequired": false, "isPreselected": false, "isManuallySelected": false, "isCodeSelected": true}, {"serial": "54", "stunum": "11*******", "department": "電機工程學系", "grade": "3", "class": "2", "priority": "1", "isRequired": false, "isPreselected": false, "isManuallySelected": false, "isCodeSelected": true}, {"serial": "55", "stunum": "11*******", "department": "電機工程學系", "grade": "3", "class": "2", "priority": "1", "isRequired": false, "isPreselected": false, "isManuallySelected": false, "isCodeSelected": true}, {"serial": "56", "stunum": "11*******", "department": "電機工程學系", "grade": "3", "class": "2", "priority": "1", "isRequired": false, "isPreselected": false, "isManuallySelected": false, "isCodeSelected": true}, {"serial": "57", "stunum": "11*******", "department": "電機工程學系", "grade": "3", "class": "2", "priority": "1", "isRequired": false, "isPreselected": false, "isManuallySelected": false, "isCodeSelected": true}, {"serial": "58", "stunum": "11*******", "department": "電機工程學系", "grade": "3", "class": "2", "priority": "1", "isRequired": false, "isPreselected": false, "isManuallySelected": false, "isCodeSelected": true}, {"serial": "59", "stunum": "11*******", "department": "電機工程學系", "grade": "3", "class": "2", "priority": "1", "isRequired": false, "isPreselected": false, "isManuallySelected": false, "isCodeSelected": true}, {"serial": "60", "stunum": "11*******", "department": "電機工程學系", "grade": "3", "class": "2", "priority": "1", "isRequired": false, "isPreselected": false, "isManuallySelected": false, "isCodeSelected": true}, {"serial": "61", "stunum": "11*******", "department": "電機工程學系", "grade": "3", "class": "2", "priority": "1", "isRequired": false, "isPreselected": false, "isManuallySelected": false, "isCodeSelected": true}, {"serial": "62", "stunum": "11*******", "department": "電機工程學系", "grade": "3", "class": "2", "priority": "1", "isRequired": false, "isPreselected": false, "isManuallySelected": false, "isCodeSelected": true}, {"serial": "63", "stunum": "11*******", "department": "電機工程學系", "grade": "3", "class": "2", "priority": "1", "isRequired": false, "isPreselected": false, "isManuallySelected": false, "isCodeSelected": true}, {"serial": "64", "stunum": "11*******", "department": "電機工程學系", "grade": "3", "class": "2", "priority": "1", "isRequired": false, "isPreselected": false, "isManuallySelected": false, "isCodeSelected": true}, {"serial": "65", "stunum": "11*******", "department": "通訊工程學系", "grade": "3", "class": "*", "priority": "1", "isRequired": false, "isPreselected": false, "isManuallySelected": false, "isCodeSelected": true}, {"serial": "66", "stunum": "11*******", "department": "電機工程學系", "grade": "3", "class": "1", "priority": "1", "isRequired": false, "isPreselected": false, "isManuallySelected": false, "isCodeSelected": true}]}