{"serial": "48046", "department_serial": 40, "code": "FMA029", "class": "*", "name": {"en": "Research Methods II", "ch": "論文研究II"}, "notice": {"en": "", "ch": ""}, "instructor": {"en": [], "ch": ["教授群"]}, "credits": 2, "time_loc": [{"time": {"week": 6, "session": ["A", "B"]}, "loc": {"building": "I1", "room": "408"}}], "isRequired": true, "isFullSem": false, "MaxStu": 40, "department": {"ch": "財務金融學系", "en": "Department of Finance"}, "system": {"ch": "碩士在職專班", "en": "Master Programme (Adult Learning)"}, "language": {"ch": "國語", "en": "Chinese"}, "card": {"ch": "不使用", "en": "None"}, "assigned": 0, "selected": 26, "remark": {"ch": "", "en": ""}, "goal": {"ch": "討論近半年來國內外財務金融相關之期刊論文", "en": "討論近半年來國內外財務金融相關之期刊論文"}, "outline": {"ch": "討論近半年來國內外財務金融相關之期刊論文", "en": "討論近半年來國內外財務金融相關之期刊論文"}, "textbook": {"ch": "依老師規定", "en": "依老師規定"}, "selfCompiledRate": {"ch": "0", "en": "0"}, "instructMethod": {"ch": "個別指導", "en": ["Individual Instruction"]}, "gradMethod": {"ch": "依老師規定", "en": "依老師規定"}, "officeHour": {"ch": "請洽老師", "en": "請洽老師"}, "teachWeeks": {"ch": "18", "en": "18"}, "flexDiscription": {"ch": "", "en": ""}, "domain": {"ch": "基礎學科\n\n\n、\n\n\n數量方法\n\n\n、\n\n\n公司理財\n\n\n、\n\n\n金融商品及投資\n\n\n、\n\n\n金融市場\n\n\n、\n\n\n保險\n\n\n、\n\n\n會計\n\n\n、\n\n\n一般管理", "en": "基礎學科\n\n\n、\n\n\n數量方法\n\n\n、\n\n\n公司理財\n\n\n、\n\n\n金融商品及投資\n\n\n、\n\n\n金融市場\n\n\n、\n\n\n保險\n\n\n、\n\n\n會計\n\n\n、\n\n\n一般管理"}, "map": {"ch": [{"competencies": "管理知識", "rating": "(3)普通", "assesments": ["其他"]}, {"competencies": "獨立思考和解決問題能力", "rating": "(3)普通", "assesments": ["其他"]}, {"competencies": "國際觀", "rating": "(3)普通", "assesments": ["其他"]}, {"competencies": "社會責任", "rating": "(3)普通", "assesments": ["其他"]}, {"competencies": "溝通能力", "rating": "(3)普通", "assesments": ["其他"]}], "en": [{"competencies": "Management Knowledge", "rating": "(3)Medium", "assesments": ["Others"]}, {"competencies": "Critical Thinking and Problem-solving", "rating": "(3)Medium", "assesments": ["Others"]}, {"competencies": "Global Perspective", "rating": "(3)Medium", "assesments": ["Others"]}, {"competencies": "Social Responsibility", "rating": "(3)Medium", "assesments": ["Others"]}, {"competencies": "Communication Skill", "rating": "(3)Medium", "assesments": ["Others"]}]}, "assignCriteria": {"ch": ["系所:限財務金融學系碩士在職專班。年級:限二年級。"], "en": ["Department:Master of Finance in-service only.Year:Second Year only."]}, "preselecStu": 26, "stuGender": {"male": 11, "Female": 15}, "stuGrade": {"doctor": {}, "master": {"2": 26}, "bachelor": {}}, "stus": [{"serial": "1", "stunum": "11*******", "department": "財務金融學系碩士在職專班", "grade": "2", "class": "*", "priority": "1", "isRequired": true, "isPreselected": true, "isSelected": true}, {"serial": "2", "stunum": "11*******", "department": "財務金融學系碩士在職專班", "grade": "2", "class": "*", "priority": "1", "isRequired": true, "isPreselected": true, "isSelected": true}, {"serial": "3", "stunum": "11*******", "department": "財務金融學系碩士在職專班", "grade": "2", "class": "*", "priority": "1", "isRequired": true, "isPreselected": true, "isSelected": true}, {"serial": "4", "stunum": "11*******", "department": "財務金融學系碩士在職專班", "grade": "2", "class": "*", "priority": "1", "isRequired": true, "isPreselected": true, "isSelected": true}, {"serial": "5", "stunum": "11*******", "department": "財務金融學系碩士在職專班", "grade": "2", "class": "*", "priority": "1", "isRequired": true, "isPreselected": true, "isSelected": true}, {"serial": "6", "stunum": "11*******", "department": "財務金融學系碩士在職專班", "grade": "2", "class": "*", "priority": "1", "isRequired": true, "isPreselected": true, "isSelected": true}, {"serial": "7", "stunum": "11*******", "department": "財務金融學系碩士在職專班", "grade": "2", "class": "*", "priority": "1", "isRequired": true, "isPreselected": true, "isSelected": true}, {"serial": "8", "stunum": "11*******", "department": "財務金融學系碩士在職專班", "grade": "2", "class": "*", "priority": "1", "isRequired": true, "isPreselected": true, "isSelected": true}, {"serial": "9", "stunum": "11*******", "department": "財務金融學系碩士在職專班", "grade": "2", "class": "*", "priority": "1", "isRequired": true, "isPreselected": true, "isSelected": true}, {"serial": "10", "stunum": "11*******", "department": "財務金融學系碩士在職專班", "grade": "2", "class": "*", "priority": "1", "isRequired": true, "isPreselected": true, "isSelected": true}, {"serial": "11", "stunum": "11*******", "department": "財務金融學系碩士在職專班", "grade": "2", "class": "*", "priority": "1", "isRequired": true, "isPreselected": true, "isSelected": true}, {"serial": "12", "stunum": "11*******", "department": "財務金融學系碩士在職專班", "grade": "2", "class": "*", "priority": "1", "isRequired": true, "isPreselected": true, "isSelected": true}, {"serial": "13", "stunum": "11*******", "department": "財務金融學系碩士在職專班", "grade": "2", "class": "*", "priority": "1", "isRequired": true, "isPreselected": true, "isSelected": true}, {"serial": "14", "stunum": "11*******", "department": "財務金融學系碩士在職專班", "grade": "2", "class": "*", "priority": "1", "isRequired": true, "isPreselected": true, "isSelected": true}, {"serial": "15", "stunum": "11*******", "department": "財務金融學系碩士在職專班", "grade": "2", "class": "*", "priority": "1", "isRequired": true, "isPreselected": true, "isSelected": true}, {"serial": "16", "stunum": "11*******", "department": "財務金融學系碩士在職專班", "grade": "2", "class": "*", "priority": "1", "isRequired": true, "isPreselected": true, "isSelected": true}, {"serial": "17", "stunum": "11*******", "department": "財務金融學系碩士在職專班", "grade": "2", "class": "*", "priority": "1", "isRequired": true, "isPreselected": true, "isSelected": true}, {"serial": "18", "stunum": "11*******", "department": "財務金融學系碩士在職專班", "grade": "2", "class": "*", "priority": "1", "isRequired": true, "isPreselected": true, "isSelected": true}, {"serial": "19", "stunum": "11*******", "department": "財務金融學系碩士在職專班", "grade": "2", "class": "*", "priority": "1", "isRequired": true, "isPreselected": true, "isSelected": true}, {"serial": "20", "stunum": "11*******", "department": "財務金融學系碩士在職專班", "grade": "2", "class": "*", "priority": "1", "isRequired": true, "isPreselected": true, "isSelected": true}, {"serial": "21", "stunum": "11*******", "department": "財務金融學系碩士在職專班", "grade": "2", "class": "*", "priority": "1", "isRequired": true, "isPreselected": true, "isSelected": true}, {"serial": "22", "stunum": "11*******", "department": "財務金融學系碩士在職專班", "grade": "2", "class": "*", "priority": "1", "isRequired": true, "isPreselected": true, "isSelected": true}, {"serial": "23", "stunum": "11*******", "department": "財務金融學系碩士在職專班", "grade": "2", "class": "*", "priority": "1", "isRequired": true, "isPreselected": true, "isSelected": true}, {"serial": "24", "stunum": "11*******", "department": "財務金融學系碩士在職專班", "grade": "2", "class": "*", "priority": "1", "isRequired": true, "isPreselected": true, "isSelected": true}, {"serial": "25", "stunum": "11*******", "department": "財務金融學系碩士在職專班", "grade": "2", "class": "*", "priority": "1", "isRequired": true, "isPreselected": true, "isSelected": true}, {"serial": "26", "stunum": "11*******", "department": "財務金融學系碩士在職專班", "grade": "2", "class": "*", "priority": "1", "isRequired": true, "isPreselected": true, "isSelected": true}]}